royalnet_console/__init__.py
royalnet_console/bullets.py
royalnet_console/pda.py
royalnet_console-6.6.2.dist-info/LICENSE.txt
royalnet_console-6.6.2.dist-info/WHEEL
royalnet_console-6.6.2.dist-info/METADATA
royalnet_console-6.6.2.dist-info/RECORD
