Metadata-Version: 2.1
Name: royalnet-console
Version: 6.6.2
Summary: A terminal-based frontend for the royalnet.engineer module.
Home-page: https://github.com/Steffo99/royalnet-console
License: AGPL-3.0-or-later
Keywords: royalnet
Author: Stefano Pigozzi
Author-email: me@steffo.eu
Requires-Python: >=3.8,<4.0
Classifier: Development Status :: 3 - Alpha
Classifier: Intended Audience :: Developers
Classifier: License :: OSI Approved :: GNU Affero General Public License v3 or later (AGPLv3+)
Classifier: Operating System :: OS Independent
Classifier: Programming Language :: Python :: 3
Classifier: Programming Language :: Python :: 3.10
Classifier: Programming Language :: Python :: 3.8
Classifier: Programming Language :: Python :: 3.9
Classifier: Topic :: Terminals
Requires-Dist: click (>=7.1.2,<8.0.0)
Requires-Dist: colorama (>=0.4.4,<0.5.0)
Requires-Dist: psutil (>=5.8.0,<6.0.0)
Requires-Dist: royalnet (>=6.6.0,<6.7.0)
Project-URL: Documentation, https://royalnet-console.readthedocs.io/
Project-URL: Repository, https://github.com/Steffo99/royalnet-console
